yt_search_api/__init__.py
yt_search_api/version.py
yt_search_api/channel/__init__.py
yt_search_api/channel/channel.py
yt_search_api-1.3.1.dist-info/LICENSE
yt_search_api-1.3.1.dist-info/METADATA
yt_search_api-1.3.1.dist-info/WHEEL
yt_search_api-1.3.1.dist-info/top_level.txt
yt_search_api-1.3.1.dist-info/RECORD
