Metadata-Version: 2.1
Name: yt-search-api
Version: 1.3.1
Summary: A lightweight module to perform a Youtube search
Home-page: https://github.com/ab-anand/yt_search_api
Author: Abhinav Anand
Author-email: abhinavanand1905@gmail.com
License: MIT
Download-URL: https://github.com/ab-anand/yt_search_api/tarball/1.3.1
Keywords: Youtube,search,Automation,api
Platform: UNKNOWN
Classifier: Intended Audience :: Developers
Classifier: License :: OSI Approved :: MIT License
Classifier: Natural Language :: English
Classifier: Programming Language :: Python
Classifier: Programming Language :: Python :: 3.4
Classifier: Programming Language :: Python :: 3.6
Classifier: Programming Language :: Python :: 3.8
Classifier: Topic :: System
Classifier: Topic :: System :: Operating System
Classifier: Topic :: Utilities
Classifier: Topic :: Software Development
Classifier: Topic :: Software Development :: Libraries
Requires-Dist: pathlib (>=1.0.1)
Requires-Dist: setuptools (>=44.1.1)
Requires-Dist: requests (>=2.25.1)
